{
    "translation": {
      "error":"Ошибка",
      "removeAccount":"Удалить аккаунт",
      "alert":"Внимание",
      "delete account text1":"Удаление учетной записи TopMaster означает прощание с:",
      "delete account text2":"История заказов: Ваша история заказов будет удалена",
      "delete account text3":"Награды и баллы: накопили кучу вкусных наград? Пуф! Они исчезнут вместе с вашей учетной записью.",
      "delete account text4":"Держаться секунду! Вы можете удалить свою учетную запись только один раз в месяц. Это всего лишь мера безопасности для обеспечения безопасности вашей учетной записи.",
      "delete account text5":"Все еще хотите удалить? Мы понимаем. Если вы уверены, продолжайте. Но если у вас есть какие-либо вопросы или вы хотите поговорить о состоянии вашего аккаунта, наша дружная команда поддержки TopMaster всегда рада помочь!",
      "getCode":"получить код",
      "wrong phone number":"неправильный номер телефона",
      "wrong verification code":"пожалуйста, введите код подтверждения",
      "verification code prompt":"Мы отправили код подтверждения на ваш номер телефона. Пожалуйста, введите код здесь, чтобы продолжить",
      "successfully":"успешно",
      "account deleted successfully":"Удаление аккаунта завершено. Мы надеемся увидеть вас снова когда-нибудь!",
      "loading": "Загрузка ....",
      "Ishlari": "Работы",
      "Band qilish": "Бронировать",
      "min": "мин.",
      "sum": "сум",
      "Ish vaqti": "Рабочее время"
    }
}